felice/__init__.py
felice/__main__.py
felice/_api.py
felice/_core/__init__.py
felice/_core/utils.py
felice/_core/calcs/Calc.py
felice/_core/calcs/Draft.py
felice/_core/calcs/File.py
felice/_core/calcs/Git.py
felice/_core/calcs/Prog.py
felice/_core/calcs/Text.py
felice/_core/calcs/__init__.py
felice/drafts/gitignore.txt
felice/drafts/installation.txt
felice/tests/__init__.py
felice/tests/test_1984.py
felice-0.0.0.dev3.dist-info/licenses/LICENSE.txt
felice-0.0.0.dev3.dist-info/METADATA
felice-0.0.0.dev3.dist-info/WHEEL
felice-0.0.0.dev3.dist-info/top_level.txt
felice-0.0.0.dev3.dist-info/RECORD
