Metadata-Version: 2.4
Name: felice
Version: 0.0.0.dev3
Summary: Create/autocomplete/format a python project and upload it to PyPI.
Author-email: Johannes <johannes-programming@mailfence.com>
License: The MIT License (MIT)
Project-URL: Download, https://pypi.org/project/felice/#files
Project-URL: Index, https://pypi.org/project/felice/
Project-URL: Source, https://github.com/johannes-programming/felice/
Project-URL: Website, http://felice.johannes-programming.online/
Classifier: Development Status :: 2 - Pre-Alpha
Classifier: Intended Audience :: Developers
Classifier: License :: OSI Approved :: MIT License
Classifier: Natural Language :: English
Classifier: Operating System :: OS Independent
Classifier: Programming Language :: Python
Classifier: Programming Language :: Python :: 3
Classifier: Programming Language :: Python :: 3 :: Only
Classifier: Typing :: Typed
Requires-Python: >=3.11
License-File: LICENSE.txt
Requires-Dist: black>=24.4.2
Requires-Dist: bs4>=0.0.2
Requires-Dist: build>=1.2.1
Requires-Dist: filelisting>=1.2.4
Requires-Dist: isort>=5.9.3
Requires-Dist: requests>=2.31
Requires-Dist: tomlhold>=0.1.3
Requires-Dist: twine>=5.1.1
Requires-Dist: v440>=1.0.5
Dynamic: license-file
